genvars/__init__.py
genvars/__main__.py
genvars/core/__init__.py
genvars/core/generator.py
genvars-0.1.3.dist-info/METADATA
genvars-0.1.3.dist-info/WHEEL
genvars-0.1.3.dist-info/RECORD
